{"cameraMode":{"drawMode":0,"name":"Shaded","section":"Shading Mode"},"sceneLighting":false,"audioPlay":false,"sceneViewState":{"m_AlwaysRefresh":false,"showFog":true,"showSkybox":false,"showFlares":true,"showImageEffects":true,"showParticleSystems":true,"showVisualEffectGraphs":true,"m_FxEnabled":true},"in2DMode":false,"pivot":{"x":-30.0,"y":0.0,"z":0.0},"rotation":{"x":0.040807344019412997,"y":0.0017543379217386246,"z":-0.0023808523546904327,"w":0.9994128346443176},"size":202.23748779296876,"orthographic":false}